README.md
setup.py
kaola/__init__.py
kaola.egg-info/PKG-INFO
kaola.egg-info/SOURCES.txt
kaola.egg-info/dependency_links.txt
kaola.egg-info/requires.txt
kaola.egg-info/top_level.txt
kaola.egg-info/zip-safe
kaola/api/__init__.py
kaola/api/basic.py
kaola/api/category.py
kaola/api/delivery.py
kaola/api/kaola.py
kaola/api/order.py
kaola/api/product.py
kaola/api/service.py
kaola/api/vender.py
kaola/comm/__init__.py
kaola/comm/comm.py