Metadata-Version: 2.1
Name: kaola
Version: 0.0.9
Summary: Kaola Python SDK
Home-page: https://github.com/block-cat/kaola-sdk
Author: blackcat
Author-email: kfx2007@163.com
License: GNU
Keywords: kaola sdk
Platform: UNKNOWN
Classifier: License :: OSI Approved :: GNU Affero General Public License v3
Classifier: Programming Language :: Python
Classifier: Operating System :: OS Independent
Classifier: Topic :: Scientific/Engineering :: Astronomy
Classifier: Topic :: Scientific/Engineering :: GIS
Classifier: Topic :: Scientific/Engineering :: Mathematics
Classifier: Intended Audience :: Science/Research
Classifier: Intended Audience :: Developers
Classifier: Intended Audience :: Information Technology
Requires-Python: >=3.6
